<?xml version="1.0"?>
<!DOCTYPE hibernate-mapping PUBLIC "-//Hibernate/Hibernate Mapping DTD 3.0//EN"
"http://www.hibernate.org/dtd/hibernate-mapping-3.0.dtd">
<!-- Generated 05/02/2014 15:44:06 by Hibernate Tools 3.6.0 -->
<hibernate-mapping>
    <class name="DAO.Credencial" table="credencial" schema="public">
        <id name="idUsuario" type="int">
            <column name="id_usuario" />
            <generator class="foreign">
                <param name="property">usuario</param>
            </generator>
        </id>
        <one-to-one name="usuario" class="DAO.Usuario" constrained="true"></one-to-one>
        <property name="senha" type="string">
            <column name="senha" length="50" not-null="true" />
        </property>
        <property name="atualizadoEm" type="timestamp">
            <column name="atualizado_em" length="29" not-null="true" />
        </property>
    </class>
</hibernate-mapping>
